fmost_seg-2025.9.15.dist-info/licenses/LICENSE
nnunetv2/__init__.py
nnunetv2/configuration.py
nnunetv2/paths.py
nnunetv2/batch_running/__init__.py
nnunetv2/batch_running/collect_results_custom_Decathlon.py
nnunetv2/batch_running/collect_results_custom_Decathlon_2d.py
nnunetv2/batch_running/generate_lsf_runs_customDecathlon.py
nnunetv2/batch_running/benchmarking/__init__.py
nnunetv2/batch_running/benchmarking/generate_benchmarking_commands.py
nnunetv2/batch_running/benchmarking/summarize_benchmark_results.py
nnunetv2/batch_running/release_trainings/__init__.py
nnunetv2/batch_running/release_trainings/nnunetv2_v1/__init__.py
nnunetv2/batch_running/release_trainings/nnunetv2_v1/collect_results.py
nnunetv2/batch_running/release_trainings/nnunetv2_v1/generate_lsf_commands.py
nnunetv2/dataset_conversion/Dataset015_018_RibFrac_RibSeg.py
nnunetv2/dataset_conversion/Dataset021_CTAAorta.py
nnunetv2/dataset_conversion/Dataset023_AbdomenAtlas1_1Mini.py
nnunetv2/dataset_conversion/Dataset027_ACDC.py
nnunetv2/dataset_conversion/Dataset042_BraTS18.py
nnunetv2/dataset_conversion/Dataset043_BraTS19.py
nnunetv2/dataset_conversion/Dataset073_Fluo_C3DH_A549_SIM.py
nnunetv2/dataset_conversion/Dataset114_MNMs.py
nnunetv2/dataset_conversion/Dataset115_EMIDEC.py
nnunetv2/dataset_conversion/Dataset119_ToothFairy2_All.py
nnunetv2/dataset_conversion/Dataset120_RoadSegmentation.py
nnunetv2/dataset_conversion/Dataset137_BraTS21.py
nnunetv2/dataset_conversion/Dataset218_Amos2022_task1.py
nnunetv2/dataset_conversion/Dataset219_Amos2022_task2.py
nnunetv2/dataset_conversion/Dataset220_KiTS2023.py
nnunetv2/dataset_conversion/Dataset221_AutoPETII_2023.py
nnunetv2/dataset_conversion/Dataset223_AMOS2022postChallenge.py
nnunetv2/dataset_conversion/Dataset224_AbdomenAtlas1.0.py
nnunetv2/dataset_conversion/Dataset226_BraTS2024-BraTS-GLI.py
nnunetv2/dataset_conversion/Dataset227_TotalSegmentatorMRI.py
nnunetv2/dataset_conversion/Dataset987_dummyDataset4.py
nnunetv2/dataset_conversion/Dataset989_dummyDataset4_2.py
fmost_seg-2025.9.15.dist-info/METADATA
fmost_seg-2025.9.15.dist-info/WHEEL
fmost_seg-2025.9.15.dist-info/entry_points.txt
fmost_seg-2025.9.15.dist-info/top_level.txt
fmost_seg-2025.9.15.dist-info/RECORD
